instabot/__init__.py
instabot/singleton.py
instabot/utils.py
instabot/api/__init__.py
instabot/api/api.py
instabot/api/api_login.py
instabot/api/api_photo.py
instabot/api/api_story.py
instabot/api/api_video.py
instabot/api/config.py
instabot/api/devices.py
instabot/api/prepare.py
instabot/bot/__init__.py
instabot/bot/bot.py
instabot/bot/bot_archive.py
instabot/bot/bot_block.py
instabot/bot/bot_checkpoint.py
instabot/bot/bot_comment.py
instabot/bot/bot_delete.py
instabot/bot/bot_direct.py
instabot/bot/bot_filter.py
instabot/bot/bot_follow.py
instabot/bot/bot_get.py
instabot/bot/bot_like.py
instabot/bot/bot_photo.py
instabot/bot/bot_stats.py
instabot/bot/bot_story.py
instabot/bot/bot_support.py
instabot/bot/bot_unfollow.py
instabot/bot/bot_unlike.py
instabot/bot/bot_video.py
instabot/bot/state/__init__.py
instabot/bot/state/bot_cache.py
instabot/bot/state/bot_state.py
tests/__init__.py
tests/test_bot.py
tests/test_bot_comment.py
tests/test_bot_filter.py
tests/test_bot_follow.py
tests/test_bot_get.py
tests/test_bot_like.py
tests/test_bot_support.py
tests/test_bot_unlike.py
tests/test_variables.py
kinstabot-0.117.5.dist-info/LICENSE
kinstabot-0.117.5.dist-info/METADATA
kinstabot-0.117.5.dist-info/WHEEL
kinstabot-0.117.5.dist-info/top_level.txt
kinstabot-0.117.5.dist-info/RECORD
